ckanext/__init__.py
ckanext/pygments/__init__.py
ckanext/pygments/cache.py
ckanext/pygments/config.py
ckanext/pygments/config_declaration.yaml
ckanext/pygments/config_schema.yaml
ckanext/pygments/const.py
ckanext/pygments/helpers.py
ckanext/pygments/plugin.py
ckanext/pygments/utils.py
ckanext/pygments/views.py
ckanext/pygments/assets/webassets.yml
ckanext/pygments/assets/css/pygments.css
ckanext/pygments/assets/js/pygment-global.js
ckanext/pygments/assets/js/pygment-line-highlight.js
ckanext/pygments/assets/js/vendor/htmx.min.js
ckanext/pygments/logic/__init__.py
ckanext/pygments/logic/action.py
ckanext/pygments/logic/schema.py
ckanext/pygments/logic/validators.py
ckanext/pygments/templates/package/snippets/resource_view.html
ckanext/pygments/templates/package/snippets/view_form.html
ckanext/pygments/templates/pygments/config.html
ckanext/pygments/templates/pygments/pygment_form.html
ckanext/pygments/templates/pygments/pygment_indicator.html
ckanext/pygments/templates/pygments/pygment_preview.html
ckanext/pygments/templates/pygments/pygment_preview_body.html
ckanext_pygments-1.2.5.dist-info/licenses/LICENSE
ckanext_pygments-1.2.5.dist-info/METADATA
ckanext_pygments-1.2.5.dist-info/WHEEL
ckanext_pygments-1.2.5.dist-info/entry_points.txt
ckanext_pygments-1.2.5.dist-info/top_level.txt
ckanext_pygments-1.2.5.dist-info/RECORD
