Metadata-Version: 2.4
Name: ckanext-pygments
Version: 1.2.5
Summary: Provides previews with syntax highlight for multiple formats
Author-email: DataShades <datashades@linkdigital.com.au>, Sergey Motornyuk <sergey.motornyuk@linkdigital.com.au>, Oleksandr Cherniavskyi <mutantsan@gmail.com>
Maintainer-email: DataShades <datashades@linkdigital.com.au>
License: AGPL
Project-URL: Homepage, https://github.com/DataShades/ckanext-pygments
Keywords: CKAN
Classifier: Development Status :: 4 - Beta
Classifier: License :: OSI Approved :: GNU Affero General Public License v3 or later (AGPLv3+)
Classifier: Programming Language :: Python :: 3.8
Classifier: Programming Language :: Python :: 3.9
Classifier: Programming Language :: Python :: 3.10
License-File: LICENSE
Requires-Dist: Pygments<3.0.0,>=2.19.1
Provides-Extra: admin
Requires-Dist: ckanext-admin_panel>=1.0.14; extra == "admin"
Dynamic: license-file
